utbot_mypy_runner/__init__.py
utbot_mypy_runner/__main__.py
utbot_mypy_runner/expression_traverser.py
utbot_mypy_runner/extract_annotations.py
utbot_mypy_runner/mypy_main.py
utbot_mypy_runner/names.py
utbot_mypy_runner/nodes.py
utbot_mypy_runner/utils.py
utbot_mypy_runner-0.2.17.dist-info/METADATA
utbot_mypy_runner-0.2.17.dist-info/WHEEL
utbot_mypy_runner-0.2.17.dist-info/RECORD
