Metadata-Version: 2.1
Name: utbot_mypy_runner
Version: 0.2.17
Summary: 
Author: Ekaterina Tochilina
Author-email: katerina_t_n@mail.ru
Requires-Python: >=3.8,<4.0
Classifier: Programming Language :: Python :: 3
Classifier: Programming Language :: Python :: 3.8
Classifier: Programming Language :: Python :: 3.9
Classifier: Programming Language :: Python :: 3.10
Classifier: Programming Language :: Python :: 3.11
Requires-Dist: mypy (==1.5.1)
